flittpayments/__init__.py
flittpayments/api.py
flittpayments/checkout.py
flittpayments/configuration.py
flittpayments/exceptions.py
flittpayments/helpers.py
flittpayments/order.py
flittpayments/payment.py
flittpayments/resources.py
flittpayments/utils.py
flittpayments-1.0.4.dist-info/LICENSE
flittpayments-1.0.4.dist-info/METADATA
flittpayments-1.0.4.dist-info/WHEEL
flittpayments-1.0.4.dist-info/top_level.txt
flittpayments-1.0.4.dist-info/RECORD
